bdcp/__init__.py
bdcp/connections.py
bdcp/offline.py
bdcp/js/searchAli.js
bdcp/sh/cluster.sh
bdcp/sh/demo.h5
bdcp/sh/single.sh
bdcp/sql/bd_command.sql
bdcp/sql/bd_practice.sql
bdcp/sql/bike.sql
bdcp/sql/brand.sql
bdcp/sql/comm.sql
bdcp/sql/core.sql
bdcp/sql/covid.sql
bdcp/sql/df.sql
bdcp/sql/loan.sql
bdcp/sql/mobile.sql
bdcp/sql/msg.sql
bdcp/sql/person.sql
bdcp/sql/project.sql
bdcp/sql/shop.sql
bdcp/sql/shopping.sql
bdcp/sql/stream.sql
bdcp/sql/web.sql
bdcp-1.6.8.dist-info/LICENSE
bdcp-1.6.8.dist-info/METADATA
bdcp-1.6.8.dist-info/WHEEL
bdcp-1.6.8.dist-info/top_level.txt
bdcp-1.6.8.dist-info/RECORD
