Metadata-Version: 2.1
Name: bdcp
Version: 1.6.8
Summary: A big data competition auxiliary package
Author: yiluohan1234
Author-email: XX@qq.com
Classifier: Programming Language :: Python :: 3
Classifier: License :: OSI Approved :: MIT License
Classifier: Operating System :: OS Independent
Requires-Python: >=3
License-File: LICENSE
Requires-Dist: requests
Requires-Dist: pandas
Requires-Dist: paramiko ==3.0.0
Requires-Dist: cryptography ==36.0.2
Requires-Dist: pymysql
